{"id":"489","name":"Shri Guru Sandipani Institute of Technology & Science, Ujjain","city":"Ujjain","type":"Private","university":"RGPV,BHOPAL","years":[2017,2018,2019,2020,2021,2022,2023,2024,2025],"cols":["b","yr","uni","rd","pool","fw","dom","op","cl","al"],"rows":[["civil",2025,"jee","RF","UR/X/OP",0,"",941002,1426044,2],["civil",2025,"qe","TR","UR/X/OP",0,"",5456,6208,3],["civil",2025,"qe","TR","UR/X/OP",0,"",7595,7595,1],["civil",2025,"qe","TR","UR/X/OP",0,"",7701,7701,1],["civil",2025,"qe","TR","UR/X/OP",0,"",11079,11079,1],["civil",2025,"qe","TR","UR/X/OP",0,"",3470,11250,3],["cse",2025,"jee","RF","EWS",0,"",1342751,1342751,1],["cse",2025,"qe","TR","EWS",0,"",637,637,1],["cse",2025,"jee","RF","FW/OP",1,"",1266852,1266852,1],["cse",2025,"qe","TR","FW/OP",1,"",8361,8361,1],["cse",2025,"jee","FU","UR/X/OP",0,"",205901,205901,1],["cse",2025,"jee","RF","UR/X/OP",0,"",157797,1464891,21],["cse",2025,"jee","SR","UR/X/OP",0,"",251632,606768,3],["cse",2025,"jee","SR","UR/X/OP",0,"",701941,701941,1],["cse",2025,"jee","SR","UR/X/OP",0,"",1207372,1395964,2],["cse",2025,"jee","SR","UR/X/OP",0,"",439916,1465328,3],["cse",2025,"qe","TR","UR/X/OP",0,"",481,11779,31],["cse",2025,"qe","TR","UR/X/OP",0,"",681,12301,12],["cse",2025,"qe","TR","UR/X/OP",0,"",3237,12669,12],["cse",2025,"qe","TR","UR/X/OP",0,"",1445,13279,10],["cse",2025,"qe","TR","UR/X/OP",0,"",3589,13438,15],["cse",2025,"qe","TR","UR/X/OP",0,"",450,13454,29],["ece",2025,"qe","TR","UR/X/OP",0,"",1972,1972,1],["ece",2025,"qe","TR","UR/X/OP",0,"",11401,11401,1],["ece",2025,"qe","TR","UR/X/OP",0,"",12390,12390,1],["ece",2025,"qe","TR","UR/X/OP",0,"",11696,13462,3],["mech",2025,"jee","RF","UR/X/OP",0,"",1076046,1076046,1],["mech",2025,"jee","SR","UR/X/OP",0,"",1302339,1302339,1],["mech",2025,"qe","TR","UR/X/OP",0,"",11459,11620,2],["mech",2025,"qe","TR","UR/X/OP",0,"",4471,13422,11],["mech",2025,"qe","TR","UR/X/OP",0,"",7765,13431,6],["civil",2024,"jee","RF","EWS",0,"",442937,887702,2],["civil",2024,"jee","RF","FW/OP",1,"",256168,386477,3],["civil",2024,"jee","SR","FW/OP",1,"",300409,300409,1],["civil",2024,"jee","FU","UR/X/OP",0,"",242187,242187,1],["civil",2024,"jee","RF","UR/X/OP",0,"",157334,1054206,5],["civil",2024,"jee","SR","UR/X/OP",0,"",208055,208055,1],["civil",2024,"qe","TR","UR/X/OP",0,"",1171,13861,17],["cse",2024,"qe","TR","EWS",0,"",3017,3017,1],["cse",2024,"jee","RF","FW/OP",1,"",101574,1408010,6],["cse",2024,"jee","FU","UR/X/OP",0,"",376406,513495,2],["cse",2024,"jee","RF","UR/X/OP",0,"",376406,1402995,18],["cse",2024,"jee","SR","UR/X/OP",0,"",390884,1315324,4],["cse",2024,"qe","TR","UR/X/OP",0,"",274,14139,111],["ece",2024,"qe","TR","EWS",0,"",12153,12153,1],["ece",2024,"jee","RF","UR/X/OP",0,"",1074604,1074604,1],["ece",2024,"jee","SR","UR/X/OP",0,"",627626,627626,1],["ece",2024,"qe","TR","UR/X/OP",0,"",610,14109,11],["mech",2024,"jee","RF","UR/X/OP",0,"",1397550,1399652,2],["mech",2024,"qe","TR","UR/X/OP",0,"",1919,13696,10],["civil",2023,"jee","RF","FW/OP",1,"",233100,233100,1],["civil",2023,"jee","SR","FW/OP",1,"",172753,172753,1],["civil",2023,"jee","RF","OBC/X/OP",0,"",804002,804002,1],["civil",2023,"jee","RF","SC/X/OP",0,"",828955,828955,1],["civil",2023,"jee","RF","UR/X/OP",0,"",192658,773282,4],["civil",2023,"qe","TR","UR/X/OP",0,"",1886,13164,27],["cse",2023,"qe","TR","EWS",0,"",1537,4411,2],["cse",2023,"jee","RF","FW/OP",1,"",19218,19218,1],["cse",2023,"qe","TR","FW/OP",1,"",363,3831,4],["cse",2023,"jee","SR","FW/OP",1,"",994201,994201,1],["cse",2023,"jee","RF","OBC/X/OP",0,"",386629,891475,7],["cse",2023,"jee","SR","OBC/X/OP",0,"",541521,894716,3],["cse",2023,"jee","RF","SC/X/OP",0,"",1001263,1069911,4],["cse",2023,"jee","RF","UR/X/OP",0,"",256031,969694,6],["cse",2023,"jee","FU","UR/X/OP",0,"",510841,510841,1],["cse",2023,"qe","TR","UR/X/OP",0,"",15,13285,102],["ece",2023,"jee","RF","OBC/X/OP",0,"",218262,218262,1],["ece",2023,"jee","RF","UR/X/OP",0,"",106394,106394,1],["ece",2023,"qe","TR","UR/X/OP",0,"",2543,12905,10],["mech",2023,"jee","RF","SC/X/OP",0,"",1060384,1060384,1],["mech",2023,"qe","TR","UR/X/OP",0,"",5737,13174,17],["civil",2022,"jee","RF","OBC/X/OP",0,"",589767,813304,2],["civil",2022,"jee","SR","OBC/X/OP",0,"",829231,829231,1],["civil",2022,"jee","RF","UR/X/OP",0,"",144376,144376,1],["civil",2022,"jee","FU","UR/X/OP",0,"",144376,144376,1],["civil",2022,"qe","TR","UR/X/OP",0,"",793,12633,26],["cse",2022,"qe","TR","EWS",0,"",2006,11918,5],["cse",2022,"jee","RF","FW/OP",1,"",265515,866325,3],["cse",2022,"jee","SR","FW/OP",1,"",721771,721771,1],["cse",2022,"jee","RF","OBC/X/OP",0,"",595137,888060,6],["cse",2022,"jee","SR","OBC/X/OP",0,"",557510,812922,2],["cse",2022,"jee","RF","SC/X/OP",0,"",600750,761614,5],["cse",2022,"jee","SR","SC/X/OP",0,"",630663,630663,1],["cse",2022,"jee","RF","ST/X/OP",0,"",623180,623180,1],["cse",2022,"jee","SR","ST/X/OP",0,"",553519,553519,1],["cse",2022,"jee","RF","UR/X/OP",0,"",147402,147402,1],["cse",2022,"qe","TR","UR/X/OP",0,"",165,12550,100],["cse",2022,"jee","SR","UR/X/OP",0,"",363758,455057,2],["ece",2022,"jee","RF","OBC/X/OP",0,"",674282,889365,2],["ece",2022,"jee","RF","UR/X/OP",0,"",534151,534151,1],["ece",2022,"qe","TR","UR/X/OP",0,"",451,11077,15],["ece",2022,"jee","SR","UR/X/OP",0,"",100753,100753,1],["mech",2022,"qe","TR","UR/X/OP",0,"",2031,12253,14],["civil",2021,"qe","TR","EWS",0,"",9641,9641,1],["civil",2021,"jee","RF","FW/OP",1,"",370829,469224,3],["civil",2021,"jee","RF","OBC/X/OP",0,"",426557,763980,3],["civil",2021,"jee","RF","UR/X/OP",0,"",605042,605042,1],["civil",2021,"qe","TR","UR/X/OP",0,"",291,14389,49],["cse",2021,"qe","TR","EWS",0,"",1356,11800,6],["cse",2021,"jee","RF","FW/OP",1,"",368511,738237,3],["cse",2021,"jee","FU","FW/OP",1,"",808432,808432,1],["cse",2021,"jee","SR","FW/OP",1,"",801714,801714,1],["cse",2021,"jee","RF","OBC/X/OP",0,"",351614,769516,6],["cse",2021,"jee","FU","OBC/X/OP",0,"",351614,351614,1],["cse",2021,"jee","SR","OBC/X/OP",0,"",637122,674005,2],["cse",2021,"jee","RF","SC/X/OP",0,"",742156,742156,1],["cse",2021,"qe","TR","UR/X/OP",0,"",354,9998,52],["cse",2021,"jee","SR","UR/X/OP",0,"",394695,775627,3],["ece",2021,"jee","SR","SC/X/OP",0,"",700621,700621,1],["ece",2021,"qe","TR","UR/X/OP",0,"",143,14468,50],["mech",2021,"jee","RF","FW/OP",1,"",521150,521150,1],["mech",2021,"jee","RF","OBC/X/OP",0,"",736563,772235,2],["mech",2021,"jee","SR","SC/X/OP",0,"",733850,733850,1],["mech",2021,"qe","TR","UR/X/OP",0,"",140,14077,50],["civil",2020,"jee","RF","FW/OP",1,"",133549,218749,2],["civil",2020,"jee","SR","FW/OP",1,"",378488,533139,3],["civil",2020,"jee","RF","OBC/X/OP",0,"",532334,978090,3],["civil",2020,"jee","FU","OBC/X/OP",0,"",562423,562423,1],["civil",2020,"jee","SR","ST/X/OP",0,"",527210,527210,1],["civil",2020,"qe","TR","UR/X/OP",0,"",754,8710,38],["civil",2020,"jee","SR","UR/X/OP",0,"",166129,958887,5],["cse",2020,"jee","RF","EWS",0,"",836832,836832,1],["cse",2020,"qe","TR","EWS",0,"",5046,5046,1],["cse",2020,"jee","RF","FW/OP",1,"",761958,761958,1],["cse",2020,"jee","RF","OBC/X/OP",0,"",416168,1004174,6],["cse",2020,"jee","SR","OBC/X/OP",0,"",204261,326006,2],["cse",2020,"jee","SR","SC/X/OP",0,"",519414,519414,1],["cse",2020,"jee","RF","UR/X/OP",0,"",257305,983900,5],["cse",2020,"qe","TR","UR/X/OP",0,"",153,7485,49],["cse",2020,"jee","FU","UR/X/OP",0,"",461028,461028,1],["ece",2020,"jee","RF","FW/OP",1,"",763778,795120,2],["ece",2020,"jee","RF","OBC/X/OP",0,"",292313,462430,2],["ece",2020,"jee","SR","OBC/X/OP",0,"",756325,756325,1],["ece",2020,"qe","TR","UR/X/OP",0,"",1916,8892,24],["mech",2020,"jee","RF","FW/OP",1,"",535499,670673,3],["mech",2020,"jee","RF","OBC/X/OP",0,"",1018888,1018888,1],["mech",2020,"jee","RF","SC/X/OP",0,"",1002882,1002882,1],["mech",2020,"jee","RF","UR/X/OP",0,"",1013270,1013270,1],["mech",2020,"qe","TR","UR/X/OP",0,"",136,8887,41],["civil",2019,"jee","SR","FW",1,"",480753,480753,1],["civil",2019,"jee","RF","OBC/X/OP",0,"",661613,875764,2],["civil",2019,"jee","SR","ST/X/OP",0,"",697533,697533,1],["civil",2019,"jee","FU","UR/X/OP",0,"",88367,88367,1],["civil",2019,"jee","RF","UR/X/OP",0,"",88367,476942,2],["civil",2019,"qe","TR","UR/X/OP",0,"",68,7552,34],["civil",2019,"jee","SR","UR/X/OP",0,"",465496,465496,1],["civil",2019,"jee","FU","UR/X/OP",0,"",88367,88367,1],["cse",2019,"jee","RF","EWS",0,"",892915,892915,1],["cse",2019,"jee","SR","EWS",0,"",184446,184446,1],["cse",2019,"jee","RF","FW",1,"",222906,646001,3],["cse",2019,"jee","SR","FW",1,"",104497,104497,1],["cse",2019,"jee","FU","FW",1,"",222906,658770,2],["cse",2019,"jee","RF","OBC/X/OP",0,"",289508,1069047,7],["cse",2019,"jee","SR","OBC/X/OP",0,"",303980,400621,2],["cse",2019,"jee","RF","SC/X/OP",0,"",789848,1114451,3],["cse",2019,"jee","SR","SC/X/OP",0,"",1084463,1084463,1],["cse",2019,"jee","RF","UR/X/OP",0,"",190925,1140953,5],["cse",2019,"qe","TR","UR/X/OP",0,"",252,7096,46],["cse",2019,"jee","SR","UR/X/OP",0,"",944157,1078081,2],["ece",2019,"jee","RF","FW",1,"",328842,400621,3],["ece",2019,"jee","RF","OBC/X/OP",0,"",912088,979096,2],["ece",2019,"jee","RF","UR/X/OP",0,"",442420,908090,2],["ece",2019,"qe","TR","UR/X/OP",0,"",173,7516,30],["mech",2019,"jee","RF","FW",1,"",998777,998777,1],["mech",2019,"jee","RF","SC/X/OP",0,"",1145735,1145735,1],["mech",2019,"jee","SR","SC/X/OP",0,"",1070479,1070479,1],["mech",2019,"jee","RF","UR/X/OP",0,"",139431,139431,1],["mech",2019,"qe","TR","UR/X/OP",0,"",479,7400,35],["mech",2019,"jee","SR","UR/X/OP",0,"",929459,1000638,2],["civil",2018,"jee","FU","OBC/X/OP",0,"",626922,626922,1],["civil",2018,"jee","RF","OBC/X/OP",0,"",418762,626922,3],["civil",2018,"jee","RF","SC/X/OP",0,"",578057,718058,2],["civil",2018,"jee","SR","UR/X/OP",0,"",773660,773660,1],["civil",2018,"qe","TR","UR/X/OP",0,"",1201,9004,33],["cse",2018,"jee","RF","FW/X/OP",1,"",108669,863647,2],["cse",2018,"jee","SR","FW/X/OP",1,"",836482,836482,1],["cse",2018,"jee","RF","OBC/X/OP",0,"",268013,268013,1],["cse",2018,"jee","RF","UR/X/OP",0,"",512533,608979,2],["cse",2018,"jee","SR","UR/X/OP",0,"",564101,564101,1],["cse",2018,"qe","TR","UR/X/OP",0,"",444,9153,41],["ece",2018,"jee","RF","FW/X/OP",1,"",612008,612008,1],["ece",2018,"jee","RF","UR/X/OP",0,"",663695,663695,1],["ece",2018,"jee","SR","UR/X/OP",0,"",85978,555255,2],["ece",2018,"qe","TR","UR/X/OP",0,"",1195,9109,26],["mech",2018,"jee","RF","FW/X/OP",1,"",651274,968728,2],["mech",2018,"jee","RF","OBC/X/OP",0,"",882913,882913,1],["mech",2018,"jee","RF","UR/X/OP",0,"",578174,683217,2],["mech",2018,"qe","TR","UR/X/OP",0,"",899,9037,31],["civil",2017,"jee","FU","FW/X/OP",1,"",203336,246057,2],["civil",2017,"jee","SR","FW/X/OP",1,"",674116,884875,2],["civil",2017,"jee","RF","FW/X/OP",1,"",203336,436783,3],["civil",2017,"jee","FU","OBC/X/OP",0,"",78348,78348,1],["civil",2017,"jee","SR","OBC/X/OP",0,"",1005746,1005746,1],["civil",2017,"jee","RF","OBC/X/OP",0,"",78348,906015,4],["civil",2017,"jee","FU","SC/X/OP",0,"",673964,673964,1],["civil",2017,"jee","RF","SC/X/OP",0,"",278892,1028936,7],["civil",2017,"jee","RF","ST/X/OP",0,"",887335,970601,2],["civil",2017,"jee","FU","UR/X/OP",0,"",474831,474831,1],["civil",2017,"jee","SR","UR/X/OP",0,"",582238,839027,3],["civil",2017,"qe","TR","UR/X/OP",0,"",219,7663,37],["civil",2017,"jee","RF","UR/X/OP",0,"",139744,748430,3],["cse",2017,"jee","FU","FW/X/OP",1,"",884875,884875,1],["cse",2017,"jee","SR","FW/X/OP",1,"",387360,597617,2],["cse",2017,"jee","RF","FW/X/OP",1,"",768835,884875,2],["cse",2017,"jee","SR","OBC/X/OP",0,"",771974,771974,1],["cse",2017,"jee","RF","OBC/X/OP",0,"",657246,967232,4],["cse",2017,"jee","RF","ST/X/OP",0,"",871872,871872,1],["cse",2017,"jee","FU","UR/X/OP",0,"",220573,695281,3],["cse",2017,"jee","SR","UR/X/OP",0,"",329002,329002,1],["cse",2017,"qe","TR","UR/X/OP",0,"",141,7339,49],["cse",2017,"jee","RF","UR/X/OP",0,"",220573,923625,5],["ece",2017,"jee","FU","FW/X/OP",1,"",992441,996133,2],["ece",2017,"jee","RF","FW/X/OP",1,"",992441,996133,2],["ece",2017,"jee","RF","OBC/X/OP",0,"",989347,989347,1],["ece",2017,"jee","SR","UR/X/OP",0,"",927902,927902,1],["ece",2017,"qe","TR","UR/X/OP",0,"",494,7690,19],["ece",2017,"jee","RF","UR/X/OP",0,"",730549,730549,1],["mech",2017,"jee","FU","FW/X/OP",1,"",170063,709360,3],["mech",2017,"jee","SR","FW/X/OP",1,"",992441,996133,2],["mech",2017,"jee","RF","FW/X/OP",1,"",170063,608286,3],["mech",2017,"jee","FU","OBC/X/OP",0,"",628890,628890,1],["mech",2017,"jee","SR","OBC/X/OP",0,"",362724,362724,1],["mech",2017,"jee","RF","OBC/X/OP",0,"",391527,896486,9],["mech",2017,"jee","RF","SC/X/OP",0,"",152837,662299,4],["mech",2017,"jee","RF","ST/X/OP",0,"",991082,991082,1],["mech",2017,"jee","SR","UR/X/OP",0,"",319684,334736,3],["mech",2017,"jee","SR","UR/X/OP",0,"",329596,329596,1],["mech",2017,"qe","TR","UR/X/OP",0,"",161,7532,33],["mech",2017,"jee","RF","UR/X/OP",0,"",132582,674116,2]]}