{"id":"h29","name":"Oriental Institute of Science & Technology, Jabalpur","city":"Jabalpur","type":"Private","university":null,"years":[2017,2018,2019,2020,2021,2022,2023,2024],"cols":["b","yr","uni","rd","pool","fw","dom","op","cl","al"],"rows":[["civil",2024,"qe","TR","UR/X/OP",0,"",7126,10769,4],["cse",2024,"jee","FU","EWS",0,"",321020,321020,1],["cse",2024,"jee","RF","EWS",0,"",321020,321020,1],["cse",2024,"qe","TR","UR/X/OP",0,"",12326,12326,1],["eee",2024,"qe","TR","UR/X/OP",0,"",842,14120,8],["mech",2024,"qe","TR","UR/X/OP",0,"",3579,14137,3],["cse",2023,"jee","RF","FW/OP",1,"",712796,712796,1],["cse",2023,"jee","FU","FW/OP",1,"",712796,712796,1],["cse",2023,"jee","SR","FW/OP",1,"",388767,530197,2],["cse",2023,"jee","RF","OBC/X/OP",0,"",431488,431488,1],["cse",2023,"jee","SR","OBC/X/OP",0,"",1088528,1088528,1],["cse",2023,"jee","RF","UR/X/OP",0,"",405874,869384,5],["cse",2023,"jee","FU","UR/X/OP",0,"",434021,476134,3],["cse",2023,"qe","TR","UR/X/OP",0,"",1757,11841,4],["cse",2023,"jee","SR","UR/X/OP",0,"",471917,496223,2],["ece",2023,"jee","RF","OBC/X/OP",0,"",201096,201096,1],["eee",2023,"qe","TR","UR/X/OP",0,"",8560,8560,1],["civil",2022,"qe","TR","UR/X/OP",0,"",9693,12039,2],["cse",2022,"jee","SR","OBC/X/OP",0,"",581896,581896,1],["cse",2022,"jee","RF","UR/X/OP",0,"",215121,811519,9],["cse",2022,"jee","FU","UR/X/OP",0,"",811519,811519,1],["cse",2022,"qe","TR","UR/X/OP",0,"",1165,12789,6],["cse",2022,"jee","SR","UR/X/OP",0,"",430873,502732,2],["ece",2022,"qe","TR","UR/X/OP",0,"",7303,7303,1],["eee",2022,"qe","TR","UR/X/OP",0,"",5349,5349,1],["mech",2022,"qe","TR","UR/X/OP",0,"",8001,8001,1],["cse",2021,"qe","TR","EWS",0,"",8727,8727,1],["cse",2021,"jee","SR","EWS",0,"",357420,485866,2],["cse",2021,"jee","RF","OBC/X/OP",0,"",807233,807233,1],["cse",2021,"jee","RF","UR/X/OP",0,"",236027,842357,5],["cse",2021,"qe","TR","UR/X/OP",0,"",4967,13944,6],["cse",2021,"jee","SR","UR/X/OP",0,"",136007,316147,2],["eee",2021,"qe","TR","UR/X/OP",0,"",13559,13559,1],["mech",2021,"qe","TR","UR/X/OP",0,"",3918,10723,4],["civil",2020,"qe","TR","UR/X/OP",0,"",5144,6631,2],["cse",2020,"jee","RF","EWS",0,"",385046,385046,1],["cse",2020,"jee","SR","OBC/X/OP",0,"",880023,880023,1],["cse",2020,"jee","RF","UR/X/OP",0,"",160217,583589,5],["cse",2020,"qe","TR","UR/X/OP",0,"",421,7566,5],["eee",2020,"qe","TR","UR/X/OP",0,"",1222,5675,2],["civil",2019,"jee","RF","ST/X/OP",0,"",955218,955218,1],["civil",2019,"qe","TR","UR/X/OP",0,"",2072,6185,2],["cse",2019,"jee","RF","OBC/X/OP",0,"",192347,192347,1],["cse",2019,"jee","RF","UR/X/OP",0,"",302170,920490,5],["cse",2019,"qe","TR","UR/X/OP",0,"",1019,5860,6],["cse",2019,"jee","FU","UR/X/OP",0,"",622219,622219,1],["eee",2019,"jee","RF","UR/X/OP",0,"",702478,702478,1],["eee",2019,"qe","TR","UR/X/OP",0,"",7489,7489,1],["cse",2018,"jee","RF","OBC/X/OP",0,"",351394,461509,2],["cse",2018,"jee","FU","UR/X/OP",0,"",135515,541333,2],["cse",2018,"jee","RF","UR/X/OP",0,"",135515,874050,3],["cse",2018,"jee","SR","UR/X/OP",0,"",895080,895080,1],["ece",2018,"jee","RF","UR/X/OP",0,"",979292,979292,1],["ece",2018,"qe","TR","UR/X/OP",0,"",7205,7205,1],["mech",2018,"jee","RF","UR/X/OP",0,"",819363,819363,1],["civil",2017,"jee","FU","FW/X/OP",1,"",257457,257457,1],["civil",2017,"jee","SR","FW/X/OP",1,"",200035,499007,2],["civil",2017,"jee","RF","FW/X/OP",1,"",129623,270471,3],["civil",2017,"jee","SR","ST/X/OP",0,"",545603,545603,1],["civil",2017,"jee","RF","UR/X/OP",0,"",401634,940798,2],["cse",2017,"jee","FU","UR/X/OP",0,"",92784,444386,2],["cse",2017,"jee","RF","UR/X/OP",0,"",92784,1005073,5],["mech",2017,"jee","FU","UR/X/OP",0,"",195571,195571,1],["mech",2017,"jee","RF","UR/X/OP",0,"",195571,292896,2]]}